chromobius.cpython-310-darwin.so
chromobius-1.1.0.dist-info/RECORD
chromobius-1.1.0.dist-info/LICENSE
chromobius-1.1.0.dist-info/WHEEL
chromobius-1.1.0.dist-info/top_level.txt
chromobius-1.1.0.dist-info/METADATA
chromobius/chromobius.pyi
