Metadata-Version: 2.1
Name: chromobius
Version: 1.1.0
Summary: A fast implementation of the mobius color code decoder.
Home-page: https://github.com/quantumlib/chromobius
Author: Craig Gidney
Requires-Python: >=3.10
License-File: LICENSE
Requires-Dist: numpy
Requires-Dist: stim
